{
 "name": "tile",
 "tilesize": 16,
 "sheet": "tile.png",
 "cols": 8,
 "rows": 8,
 "count": 64,
 "palette": [
  "#092626",
  "#202525",
  "#1d402a",
  "#283751",
  "#2e5831",
  "#134182",
  "#402a25",
  "#3d343a",
  "#3d5937",
  "#514434",
  "#825437",
  "#945d38",
  "#406a31",
  "#557c23",
  "#a1683a",
  "#648054",
  "#718a63",
  "#98784a",
  "#8f9c75",
  "#ac743f",
  "#a9af8b",
  "#82b969",
  "#85c069",
  "#86c16a",
  "#86be69",
  "#889563",
  "#bca06e",
  "#cea773",
  "#d5af7b",
  "#68b549"
 ],
 "tiles": {
  "tile_000": {
   "index": 0,
   "col": 0,
   "row": 0,
   "solid": false,
   "rows": [
    "gfoooooooooooooo",
    "ffoooooooooooooo",
    "ttooffoooooooooo",
    "ttooffoooooooooo",
    "ooffoooooooooooo",
    "ooffoooooooooooo",
    "oooooooooooooooo",
    "oooooooooooooooo",
    "oooooooooooooooo",
    "oooooooooooooooo",
    "oooooooooooooooo",
    "oooooooooooooooo",
    "oooooooooofooooo",
    "oooooooooofooooo",
    "oooooffooooooooo",
    "ooooooocfnoooooo"
   ]
  },
  "tile_001": {
   "index": 1,
   "col": 1,
   "row": 0,
   "solid": false,
   "rows": [
    "oooooooooooooooo",
    "oooooooooooooooo",
    "oooooooooooooooo",
    "ocfooofcoooooooo",
    "offoooffoooooooo",
    "offonoffoooooooo",
    "oooofoooooooolss",
    "ooooooooooooonfn",
    "ooooooooooooontn",
    "ooooooooooooooof",
    "ooooooooooooooot",
    "oooooooooooooooo",
    "oooooooooooooooo",
    "oooooooooooooooo",
    "oooooooooooooooo",
    "ooooooooooooooff"
   ]
  },
  "tile_002": {
   "index": 2,
   "col": 2,
   "row": 0,
   "solid": false,
   "rows": [
    "ooooooooootffoto",
    "ooooooooootffoto",
    "oooooooooooooooo",
    "ossooooooooooooo",
    "ossooooooooooooo",
    "onnookoooooooooo",
    "onnoosoooooooooo",
    "soooktoooooooooo",
    "soolktoooooooooo",
    "fooofloooooooooo",
    "toootooooooooooo",
    "oooooooooooooooo",
    "oooooooooooooooo",
    "oooooooooooooooo",
    "oooooooooooooooo",
    "oooooooooooooooo"
   ]
  },
  "tile_003": {
   "index": 3,
   "col": 3,
   "row": 0,
   "solid": false,
   "rows": [
    "oooooooooooooooo",
    "oooooooooooooogf",
    "ooooooooooofootf",
    "ooooooooooofoott",
    "ooooooooooooffoo",
    "ooooooooooooffoo",
    "oooooooooooooooo",
    "oooooooooooooooo",
    "oooooooooooooooo",
    "oooooooooooooooo",
    "oooooooooooooooo",
    "oooooocooooooooo",
    "oooooonooooooooo",
    "oooooooooooooooo",
    "offooooooooooooo",
    "ooofoooooooooooo"
   ]
  },
  "tile_004": {
   "index": 4,
   "col": 4,
   "row": 0,
   "solid": false,
   "rows": [
    "oooooooooooooooo",
    "oooooooooooooooo",
    "ooffoooooooooooo",
    "ooffooooooooooof",
    "ffnoooooooooooof",
    "ffooooooooooooot",
    "oooooooooooooooo",
    "oooooooooooooooo",
    "oooooooooooooooo",
    "oooooooooooooooo",
    "oooooooooooooooo",
    "oooooooooooooooo",
    "oooooooooooooooo",
    "oooooooooooooooo",
    "oooooooooooooooo",
    "ooooooossooooooo"
   ]
  },
  "tile_005": {
   "index": 5,
   "col": 5,
   "row": 0,
   "solid": false,
   "rows": [
    "oooooooooooooooo",
    "oooooooooooooooo",
    "oooooooooooooooo",
    "ctoocfoooooooooo",
    "ftoofcoooooooool",
    "flnoffoooooooooo",
    "oofnoooooooossoo",
    "ooooooooooootfso",
    "oooooooooooottso",
    "oooooooooooooofo",
    "ooooooooooooooto",
    "oooooooooooooooo",
    "oooooooooooooooo",
    "oooooooooooooooo",
    "oooooooooooooooo",
    "ooooooooooooffoo"
   ]
  },
  "tile_006": {
   "index": 6,
   "col": 6,
   "row": 0,
   "solid": false,
   "rows": [
    "oooooooolffofooo",
    "ooooooootffofooo",
    "nooooooooooooooo",
    "ssoooooooooooooo",
    "ssoooooooooooooo",
    "nnoooooooooooooo",
    "nnossooooooooooo",
    "oonftooooooooooo",
    "oosttooooooooooo",
    "ootooooooooooooo",
    "ootooooooooooooo",
    "oooooooooooooooo",
    "oooooooooooooooo",
    "oooooooooooooooo",
    "ooooooooooooooof",
    "oooooooooooooooo"
   ]
  },
  "tile_007": {
   "index": 7,
   "col": 7,
   "row": 0,
   "solid": false,
   "rows": [
    "oooooooooooooooo",
    "ooooooooooooofoo",
    "ooooooooofcoofoo",
    "oooooooooffootoo",
    "oooooooooooffoff",
    "oooooooooooffoff",
    "oooooooooooooooo",
    "oooooooooooooooo",
    "oooooooooooooooo",
    "oooooooooooooooo",
    "oooooooooooooooo",
    "oooofooooooooooo",
    "oooooooooooooooo",
    "oooooooooooooooo",
    "fooooooooooooooo",
    "oflooooooooooooo"
   ]
  },
  "tile_008": {
   "index": 8,
   "col": 0,
   "row": 1,
   "solid": false,
   "rows": [
    "ooooooocfooooooo",
    "oooooooooooooooo",
    "oooooooooooooooo",
    "oooooooooooooooo",
    "oooooooooooooooo",
    "oooooooooooooooo",
    "oooooooooooooooo",
    "oooooooooooftooo",
    "oooooooooooooooo",
    "oooooooooooooooo",
    "oooooooooooooooo",
    "oooooooooooooooo",
    "oosooooooooooooo",
    "ooklooooooooooco",
    "oonolssoooooooof",
    "oonolssoooooooof"
   ]
  },
  "tile_009": {
   "index": 9,
   "col": 1,
   "row": 1,
   "solid": false,
   "rows": [
    "ooooooooooooooff",
    "ooooooooooooooff",
    "ooooooooootfloff",
    "oooooooooolftnff",
    "oooooooooooolfol",
    "oooooooooooooooo",
    "oooooooooooooooo",
    "oooooooooooooooo",
    "oooooooooooooooo",
    "oooooooooooooooo",
    "ooffoooooooooooo",
    "ooffoooooooooooo",
    "oofcoooooooooooo",
    "ootfoffooooooooo",
    "ftoofooooooooooo",
    "floofooooooooooo"
   ]
  },
  "tile_010": {
   "index": 10,
   "col": 2,
   "row": 1,
   "solid": false,
   "rows": [
    "oooooooooooooooo",
    "oooooooooooooooo",
    "offnoooooooooooo",
    "offnoooooooooooo",
    "fnoooooooooooooo",
    "ooooooooooooooff",
    "ooooooooooooooff",
    "oooooooooooftoff",
    "ooooooooooooofoo",
    "ooooooooooooofoo",
    "oooooooooooooooo",
    "oooooooooooooooo",
    "oooooooooooooooo",
    "oooooooooooooooo",
    "ooooofnooooooooo",
    "ooooofnooooooooo"
   ]
  },
  "tile_011": {
   "index": 11,
   "col": 3,
   "row": 1,
   "solid": false,
   "rows": [
    "ooofoooooooooooo",
    "oootoooooooooooo",
    "oooooooooooooooo",
    "oooooooooooooooo",
    "oooooooooooofooo",
    "oooooooooooofooo",
    "oooooooooooooooo",
    "oolfoooooooooooo",
    "cflooooooooooooo",
    "fflooooooooooooo",
    "oooooooooooooooo",
    "oooooooooooooooo",
    "oooooooooooooooo",
    "ooooooooooosoooo",
    "ooooooooooosoooo",
    "ooooooooooonoooo"
   ]
  },
  "tile_012": {
   "index": 12,
   "col": 4,
   "row": 1,
   "solid": false,
   "rows": [
    "ooooooonnooooooo",
    "ooooooonnoossooo",
    "oooosoonnoossooo",
    "ooookksoonknnooo",
    "oooolffooffooooo",
    "oooooffooffooooo",
    "oooooooooooooooo",
    "oooooooooooooooo",
    "oooooooooooooooo",
    "oooooooooooooooo",
    "oooooooooooooooo",
    "oooooooooooooooo",
    "oooooooooooooooo",
    "oooooooooooonfon",
    "ooooooooooooooff",
    "ooooooooooooooff"
   ]
  },
  "tile_013": {
   "index": 13,
   "col": 5,
   "row": 1,
   "solid": false,
   "rows": [
    "ooooooooooooffoo",
    "ooooooooooooffoo",
    "ooooooooofooftoo",
    "ooooooooofootfoo",
    "oooooooooofflonf",
    "oooooooooooooooo",
    "oooooooooooooooo",
    "oooooooooooooooo",
    "oooooooooooooooo",
    "oooooooooooooooo",
    "ffoooooooooooooo",
    "ffoooooooooooooo",
    "ffoooooooooooooo",
    "tfooftoooooooooo",
    "oofloooooooooooo",
    "oofooooooooooooo"
   ]
  },
  "tile_014": {
   "index": 14,
   "col": 6,
   "row": 1,
   "solid": false,
   "rows": [
    "oooooooooooooooo",
    "oooooooooooooooo",
    "ffoooooooooooooo",
    "ffoooooooooooooo",
    "oooooooooooooooo",
    "ooooooooooooffoo",
    "ooooooooooooffoo",
    "oooooooooffoffoo",
    "ooooooooooofooff",
    "ooooooooooofooff",
    "oooooooooooooooo",
    "oooooooooooooooo",
    "oooooooooooooooo",
    "oooooooooooooooo",
    "oooffooooooooooo",
    "oooffooooooooooo"
   ]
  },
  "tile_015": {
   "index": 15,
   "col": 7,
   "row": 1,
   "solid": false,
   "rows": [
    "oflooooooooooooo",
    "otlooooooooooooo",
    "oooooooooooooooo",
    "oooooooooooooooo",
    "oooooooooffooooo",
    "oooooooooffooooo",
    "oooooooooooooooo",
    "nfoooooooooooooo",
    "cooooooooooooooo",
    "cooooooooooooooo",
    "oooooooooooooooo",
    "oooooooooooooooo",
    "ooooooooooooosoo",
    "oooooooooooookoo",
    "ooooooooooooonoo",
    "oooooooooosnonoo"
   ]
  },
  "tile_016": {
   "index": 16,
   "col": 0,
   "row": 2,
   "solid": false,
   "rows": [
    "noonnnnooooooooo",
    "kooccooooooooooo",
    "tooffooooooooooo",
    "oooooooooooooooo",
    "oooooooooooooooo",
    "oooooooooooooooo",
    "oooooooooooooooo",
    "oooooooooooooooo",
    "oooooooooggooooo",
    "oooooooooffooooo",
    "ooooooooooooooo4",
    "ooooooooooooooof",
    "oooooooooooooofo",
    "oooooooooooooofo",
    "oooooooooooooooo",
    "oooooooooooooooo"
   ]
  },
  "tile_017": {
   "index": 17,
   "col": 1,
   "row": 2,
   "solid": false,
   "rows": [
    "oooooooooooooooo",
    "oooooooooooooooo",
    "oooooooooooooooo",
    "oooooooooooooooo",
    "oooooooooooooooo",
    "oooooooooooooooo",
    "oooooooooooooooo",
    "oooooooooooolfoo",
    "oooooooooooolfoo",
    "ooooooooffooltoo",
    "fnoooooonoccnoff",
    "fnooooooooffnoff",
    "oooooooooottoott",
    "oooooooooooooooo",
    "oooooooooooooooo",
    "oooooooooooooooo"
   ]
  },
  "tile_018": {
   "index": 18,
   "col": 2,
   "row": 2,
   "solid": false,
   "rows": [
    "oooooooooooooooo",
    "oooooooooooooooo",
    "oooooooooooooooo",
    "offooooooooooooo",
    "offooooooooooooo",
    "ottooooooooooooo",
    "oooooooooooooooo",
    "oooooooooooooooo",
    "oooooooooooooooo",
    "fooooooooooooooo",
    "noooooooooooooff",
    "ooooooooooooooff",
    "oooooooooooffooo",
    "ooooooooooocfooo",
    "ooooooooooooocoo",
    "oooooooooooootoo"
   ]
  },
  "tile_019": {
   "index": 19,
   "col": 3,
   "row": 2,
   "solid": false,
   "rows": [
    "ooooooossoonooos",
    "oooooootfkooonnt",
    "ooooooofdkooonkt",
    "ooooooooofnooffo",
    "ooooooooofnooffo",
    "oooooooooooooooo",
    "oooooooooooooooo",
    "oooooooooooooooo",
    "oooooooooooooooo",
    "oooooooooooooooo",
    "oooooooooooooooo",
    "nooooooooooooooo",
    "ooofoooooooooooo",
    "ooofoooooooooooo",
    "tfcooooooooooooo",
    "ltgooooooooooooo"
   ]
  },
  "tile_020": {
   "index": 20,
   "col": 4,
   "row": 2,
   "solid": false,
   "rows": [
    "oooooooooooooooo",
    "oooooooooooooooo",
    "oooooooooooooooo",
    "oooooooooooooooo",
    "oooooooooooooooo",
    "oooooooooooooooo",
    "oooooooooooooooo",
    "oooooooooooooooo",
    "ooooooolgooooooo",
    "oooooooffooooooo",
    "oooooooooooooocf",
    "oooooooooooooncc",
    "oooooooooooonooo",
    "ooooooooooooncoo",
    "oooooooooooooooo",
    "oooooooooooooooo"
   ]
  },
  "tile_021": {
   "index": 21,
   "col": 5,
   "row": 2,
   "solid": false,
   "rows": [
    "oooooooooooooooo",
    "oooooooooooooooo",
    "oooooooooooooooo",
    "ooooooooooooooot",
    "ooooooooooooooot",
    "oooooooooooooool",
    "oooooooooooooooo",
    "ooooooooooffoooo",
    "ooooooooooffoooo",
    "oooooolfloftoofo",
    "oooooooolfonffoo",
    "ooooooootfooffoo",
    "ooooooooltoottoo",
    "oooooooooooooooo",
    "oooooooooooooooo",
    "oooooooooooooooo"
   ]
  },
  "tile_022": {
   "index": 22,
   "col": 6,
   "row": 2,
   "solid": false,
   "rows": [
    "oooooooooooooooo",
    "oooooooooooooooo",
    "oooooooooooooooo",
    "floooooooooooooo",
    "floooooooooooooo",
    "tooooooooooooooo",
    "oooooooooooooooo",
    "oooooooooooooooo",
    "oooooooooooooooo",
    "oooooooooooooooo",
    "ooooooooooooffoo",
    "ooooooooooooffno",
    "ooooooooocfooooo",
    "ooooooooofcooooo",
    "ooooooooooocoofc",
    "ooooooooooogoott"
   ]
  },
  "tile_023": {
   "index": 23,
   "col": 7,
   "row": 2,
   "solid": false,
   "rows": [
    "oooooooooosnoooo",
    "oooooooooofnsooo",
    "oooooooooooffnoo",
    "oooooooooooffooo",
    "oooooooooooooooo",
    "oooooooooooooooo",
    "oooooooooooooooo",
    "oooooooooooooooo",
    "oooooooooooooooo",
    "oooooooffooooooo",
    "oooooooooooooooo",
    "oooooooooooooooo",
    "ncoooooooooooooo",
    "ofoooooooooooooo",
    "cooooooooooooooo",
    "fooooooooooooooo"
   ]
  },
  "tile_024": {
   "index": 24,
   "col": 0,
   "row": 3,
   "solid": false,
   "rows": [
    "oooooooooooooooo",
    "oooooooooooooooo",
    "ccoooooooooooooo",
    "fcoooooooooooooo",
    "ttooffoooooooooo",
    "ffooffoooooooooo",
    "ooftoooooooooooo",
    "oooooooooooooooo",
    "oooooooooooooooo",
    "oooooooooooooooo",
    "oooooooooooooooo",
    "oooooooooooooooo",
    "oooooooooooooooo",
    "oooooooooooooooo",
    "oooooooooknooooo",
    "oooooooookkooooo"
   ]
  },
  "tile_025": {
   "index": 25,
   "col": 1,
   "row": 3,
   "solid": false,
   "rows": [
    "oooooooooooooooo",
    "oooooooooooooooo",
    "oooooooooooooooo",
    "oooooooooooooooo",
    "oooooooooooooooo",
    "oooooooooooooooo",
    "oooooooooooooooo",
    "ffoooffooooooooo",
    "ffoooffooooooooo",
    "oooofooooooooooo",
    "oooofooooooooooo",
    "oooooooooooooooo",
    "oooooooooooooooo",
    "oooooooooooooooo",
    "oooooooooooooooo",
    "oooooooooooooooo"
   ]
  },
  "tile_026": {
   "index": 26,
   "col": 2,
   "row": 3,
   "solid": false,
   "rows": [
    "oooooooooooooooo",
    "oooooooooooooooo",
    "oooooooooooooooo",
    "oooooooooooooooo",
    "oooooooooooooooo",
    "oooooooooooooooo",
    "oooonkoooooooooo",
    "oooonsoooooooooo",
    "ooooonoooooooooo",
    "osloonoossoooooo",
    "oslooooossoooooo",
    "ofskooknttoooooo",
    "oocfooffoooooooo",
    "ooffooffoooooooo",
    "oooooooooooooooo",
    "oooooooooooooooo"
   ]
  },
  "tile_027": {
   "index": 27,
   "col": 3,
   "row": 3,
   "solid": false,
   "rows": [
    "oooooooooooooooo",
    "oooooooooooooooo",
    "oooooooooooootgo",
    "ooooooooooooocfo",
    "ooooooooooffotto",
    "ooooooooooffofto",
    "oooooooooooofoof",
    "oooooooooooooooo",
    "oooooooooooooooo",
    "oooooooooooooooo",
    "oooooooooooooooo",
    "oooooooooooooooo",
    "oolcoooooooooooo",
    "oolfoooooooooooo",
    "oooooooooooooooo",
    "oooooooooooooooo"
   ]
  },
  "tile_028": {
   "index": 28,
   "col": 4,
   "row": 3,
   "solid": false,
   "rows": [
    "oooooooooooooooo",
    "oooooooooooooooo",
    "oooooooooooooooo",
    "oooooooooooooooo",
    "offooooooooooooo",
    "offooooooooooooo",
    "fooooooooooooooo",
    "ooooooooooooooft",
    "ooooooooooooooft",
    "oooooooooooooooo",
    "oooooooooooooooo",
    "oooooooooooooooo",
    "oooooooooooooooo",
    "oooooooooooooooo",
    "ooooooookooooooo",
    "ooooooookooooooo"
   ]
  },
  "tile_029": {
   "index": 29,
   "col": 5,
   "row": 3,
   "solid": false,
   "rows": [
    "oooooooooooooooo",
    "oooooooooooooooo",
    "oooooooooooooooo",
    "oooooooooooooooo",
    "oooooooooooooooo",
    "oooooooooooooooo",
    "oooooooooooooooo",
    "oooffloooooooooo",
    "oooffloooooooooo",
    "oofooooooooooooo",
    "oofooooooooooooo",
    "oooooooooooooooo",
    "oooooooooooooooo",
    "oooooooooooooooo",
    "oooooooooooooooo",
    "oooooooooooooooo"
   ]
  },
  "tile_030": {
   "index": 30,
   "col": 6,
   "row": 3,
   "solid": false,
   "rows": [
    "oooooooooooooooo",
    "oooooooooooooooo",
    "oooooooooooooooo",
    "oooooooooooooooo",
    "oookkooooooooooo",
    "oookkloooooooooo",
    "ssokkoosoooooooo",
    "ttsooksfoooooooo",
    "ffsooksdoooooooo",
    "oofootfnoooooooo",
    "oofootfnoooooooo",
    "oooooooooooooooo",
    "oooooooooooooooo",
    "oooooooooooooooo",
    "oooooooooooooooo",
    "oooooooooooooooo"
   ]
  },
  "tile_031": {
   "index": 31,
   "col": 7,
   "row": 3,
   "solid": false,
   "rows": [
    "oooooooooooooooo",
    "oooooooooooooooo",
    "oooooooooooooloo",
    "ooooooooooooofoo",
    "oooooooooffootoo",
    "oooooooooffootoo",
    "oooooooooooffocf",
    "oooooooooooooooo",
    "oooooooooooooooo",
    "oooooooooooooooo",
    "oooooooooooooooo",
    "oooooooooooooooo",
    "ofoooooooooooooo",
    "ofoooooooooooooo",
    "oooooooooooooooo",
    "oooooooooooooooo"
   ]
  },
  "tile_032": {
   "index": 32,
   "col": 0,
   "row": 4,
   "solid": false,
   "rows": [
    "oooooosolnkossoo",
    "oooooofssoosffoo",
    "oooooofssolsffoo",
    "oooooooffllfoooo",
    "oooooooooooooooo",
    "oooooooooooooooo",
    "oooooooooooooooo",
    "ffoooooooooooooo",
    "ffoooooooooooooo",
    "oooooooooooooooo",
    "oooooooooooooooo",
    "oooooooooooooooo",
    "oooooooooooooooo",
    "oooooooooooooooo",
    "oooooooooooooooo",
    "oooooooooooooooo"
   ]
  },
  "tile_033": {
   "index": 33,
   "col": 1,
   "row": 4,
   "solid": false,
   "rows": [
    "oooooooooooooooo",
    "oooooooooooooooo",
    "oooooooooooooooo",
    "oooooooooooooooo",
    "oooooooooooooffo",
    "ooooooooooftoffo",
    "ooooooooooftotfo",
    "ooooooooooonfoof",
    "oooooooooooofoof",
    "oooooooooooooooo",
    "oooooooooooooooo",
    "oooooooooooooooo",
    "oooooooooooooooo",
    "oooooooooooooooo",
    "oooooooooooooooo",
    "ooffoooooooooooo"
   ]
  },
  "tile_034": {
   "index": 34,
   "col": 2,
   "row": 4,
   "solid": false,
   "rows": [
    "oooooooooooooooo",
    "oooooooooooooooo",
    "oooooooooooooooo",
    "oooooooooooooooo",
    "oooooooooooooooo",
    "ofoooooooooooooo",
    "ofoooooooooooooo",
    "fooooooooooooooo",
    "fooooooooooooooo",
    "oooooooooooooooo",
    "oooooooooooooooo",
    "oooooooooooooooo",
    "oooooooooooooooo",
    "ooooooooooooooss",
    "oooooooooooooonn",
    "ooffooooooossonn"
   ]
  },
  "tile_035": {
   "index": 35,
   "col": 3,
   "row": 4,
   "solid": false,
   "rows": [
    "offoffoooooooooo",
    "nfcoffoooooooooo",
    "oooooooooooooooo",
    "oooooooooooooooo",
    "oooooooooooooooo",
    "oooooooooooooolf",
    "oooooooooooooolf",
    "oooooooooooooool",
    "oooooooooooooooo",
    "oooooooooffooooo",
    "oooooooooffooooo",
    "ooooooooooofoooo",
    "ooooooooooofoooo",
    "looooooooooooooo",
    "oooooooooooooooo",
    "ooosoooooooooooo"
   ]
  },
  "tile_036": {
   "index": 36,
   "col": 4,
   "row": 4,
   "solid": false,
   "rows": [
    "ooooskookoossooo",
    "ooooflskossffooo",
    "ooooflsnossffooo",
    "oooootfllffooooo",
    "oooooooooooooooo",
    "oooooooooooooooo",
    "oooooooooooooooo",
    "oooooooooooooooo",
    "oooooooooooooooo",
    "oooooooooooooooo",
    "oooooooooooooooo",
    "oooooooooooooooo",
    "oooooooooooooooo",
    "oooooooooooooooo",
    "oooooooooooooooo",
    "oooooooooooooooo"
   ]
  },
  "tile_037": {
   "index": 37,
   "col": 5,
   "row": 4,
   "solid": false,
   "rows": [
    "oooooooooooooooo",
    "oooooooooooooooo",
    "oooooooooooooooo",
    "oooooooooooooooo",
    "oooooooooooffooo",
    "ooooooooffoffoof",
    "ooooooooffotfoof",
    "oooooooooofootfo",
    "oooooooooofooffo",
    "oooooooooooooooo",
    "oooooooooooooooo",
    "oooooooooooooooo",
    "oooooooooooooooo",
    "oooooooooooooooo",
    "oooooooooooooooo",
    "ffoooooooooooooo"
   ]
  },
  "tile_038": {
   "index": 38,
   "col": 6,
   "row": 4,
   "solid": false,
   "rows": [
    "ooooooooooooooof",
    "ooooooooooooooot",
    "oooooooooooooooo",
    "oooooooooooooooo",
    "oooooooooooooooo",
    "oooooooooooooooo",
    "nooooooooooooooo",
    "oooooooooooooffo",
    "oooooooooooooffo",
    "oooooooooooooooo",
    "oooooooooooooooo",
    "oooooooooooooooo",
    "oooooooooooooooo",
    "oooooooooooooooo",
    "oooooooooooooooo",
    "ffoooooooooooooo"
   ]
  },
  "tile_039": {
   "index": 39,
   "col": 7,
   "row": 4,
   "solid": false,
   "rows": [
    "foffoooooooooooo",
    "focfoooooooooooo",
    "oooooooooooooooo",
    "oooooooooooooooo",
    "oooooooooooooooo",
    "oooooooooooffooo",
    "oooooooooooffooo",
    "ooooooooooollooo",
    "oooooooooooooooo",
    "ofooooocfooooooo",
    "ofoooooffnoooooo",
    "oooooooooffooooo",
    "oooooooooffooooo",
    "oooooooooooooooo",
    "oooooooooooooooo",
    "oooooooooooooooo"
   ]
  },
  "tile_040": {
   "index": 40,
   "col": 0,
   "row": 5,
   "solid": false,
   "rows": [
    "oooooooooooooooo",
    "ooooooooooooooco",
    "oooooooooooooogo",
    "ooooooooooooooof",
    "ooooooooooooooof",
    "oooooooooooooooo",
    "ooolssoooooooooo",
    "oooonnoooooooooo",
    "ssolnnossloooooo",
    "ssoonnossooooooo",
    "ffkooonffooooooo",
    "ttloooottooooooo",
    "oofoootloooooooo",
    "oofooolooooooooo",
    "oooooooooooooooo",
    "oooooooooooooofo"
   ]
  },
  "tile_041": {
   "index": 41,
   "col": 1,
   "row": 5,
   "solid": false,
   "rows": [
    "ooffoooooooooooo",
    "ooffofgooooooooo",
    "oottofcooooooooo",
    "floofooooooooooo",
    "floofooooooooooo",
    "oooooooooooooooo",
    "oooooooooooooooo",
    "oooooooooooooooo",
    "oooooooooooooooo",
    "ooooooooooooofoo",
    "ooooooooffoootoo",
    "ooooooooffooofoo",
    "oooooooooofftoff",
    "ooooooooooffloff",
    "ooooooooooooooon",
    "oooooooooooooooo"
   ]
  },
  "tile_042": {
   "index": 42,
   "col": 2,
   "row": 5,
   "solid": false,
   "rows": [
    "ooffooooooossonn",
    "ooooooooooofdsoo",
    "ooooooooooooocoo",
    "oooooooooooonfoo",
    "oooooooooooooooo",
    "oooooooooooooooo",
    "oooooooooooooooo",
    "oooooooooooooooo",
    "oooooooooooooooo",
    "oooooooooooooooo",
    "fooooooooooooooo",
    "fooooooooooooooo",
    "looooooooooooooo",
    "oooooooooooooooo",
    "ooooooooooooooff",
    "oooooooooooooott"
   ]
  },
  "tile_043": {
   "index": 43,
   "col": 3,
   "row": 5,
   "solid": false,
   "rows": [
    "ooosoooooooooooo",
    "onndoooooooooooo",
    "offooooooooooooo",
    "offooooooooooooo",
    "oooooooooooooooo",
    "oooooooooooooooo",
    "oooooooooooooooo",
    "oooooooooooooooo",
    "ooooooooooooooos",
    "ooooooooooooooos",
    "ooofooooooooooof",
    "oolfooooooooooof",
    "oooooooooooooooo",
    "oooooooooooooooo",
    "oooooooooooooooo",
    "oooooooooooooooo"
   ]
  },
  "tile_044": {
   "index": 44,
   "col": 4,
   "row": 5,
   "solid": false,
   "rows": [
    "oooooooooooooooo",
    "oooooooooooonloo",
    "ooooooooooooogll",
    "ooooooooooooonff",
    "ooooooooooooonff",
    "oooooooooooooooo",
    "oossoooooooooooo",
    "ookkoooooooooooo",
    "oonnoossoooooooo",
    "oonnoossoooooooo",
    "ssoosstfoooooooo",
    "ssoossftoooooooo",
    "ffoofftooooooooo",
    "ccooffoooooooooo",
    "oooooooooooooooo",
    "ooooooooooooocoo"
   ]
  },
  "tile_045": {
   "index": 45,
   "col": 5,
   "row": 5,
   "solid": false,
   "rows": [
    "ffoooooooooooooo",
    "ftoggooooooooooo",
    "ttlffooooooooooo",
    "oofooooooooooooo",
    "oofooooooooooooo",
    "oooooooooooooooo",
    "oooooooooooooooo",
    "oooooooooooooooo",
    "oooooooooolooooo",
    "ooooooooooffoooo",
    "oooooonffottoott",
    "oooooonffotfootf",
    "ooooooooofoofflo",
    "ooooooooofooffoo",
    "oooooooooooooooo",
    "oooooooooooooooo"
   ]
  },
  "tile_046": {
   "index": 46,
   "col": 6,
   "row": 5,
   "solid": false,
   "rows": [
    "ffoooooooolsoooo",
    "oooooooooolsoooo",
    "ooooooolloonoool",
    "ooooooosooonooss",
    "ooooooosnoolooss",
    "oooooootkkookkff",
    "ooooooooccoofcoo",
    "oooooooocfooffoo",
    "oooooooooooooooo",
    "oooooooooooooooo",
    "oooooooooooooooo",
    "oooooooooooooooo",
    "oooooooooooooooo",
    "oooooooooooooooo",
    "oooooooooooofflo",
    "ooooooooooootton"
   ]
  },
  "tile_047": {
   "index": 47,
   "col": 7,
   "row": 5,
   "solid": false,
   "rows": [
    "oooooooooooooooo",
    "oooooooooooooooo",
    "oooooooooooooooo",
    "oooooooooooooooo",
    "looooooooooooooo",
    "oooooooooooooooo",
    "oooooooooooooooo",
    "oooooooooooooooo",
    "ooooooooooooooss",
    "ooooooooooooooss",
    "ofooooooooooooff",
    "ofoooooooooooott",
    "oooooooooooooooo",
    "oooooooooooooooo",
    "oooooooooooooooo",
    "oooooooooooooooo"
   ]
  },
  "tile_048": {
   "index": 48,
   "col": 0,
   "row": 6,
   "solid": false,
   "rows": [
    "oooooooooooooooo",
    "oooooooooooooooo",
    "ooooooooooofoooo",
    "oooooooooooooofo",
    "oooooooooooooofo",
    "oooooooooooooooo",
    "oooooooooooooooo",
    "fooooooooooooooo",
    "ffoooooooooooooo",
    "ttoofcoooooooooo",
    "ttooccoooooooooo",
    "ooffoooooooooooo",
    "ootloooooooooooo",
    "oooooooooooooooo",
    "oooooooooooooooo",
    "oooooooooooooooo"
   ]
  },
  "tile_049": {
   "index": 49,
   "col": 1,
   "row": 6,
   "solid": false,
   "rows": [
    "oooooooooooooooo",
    "oooooooooooooooo",
    "oooooooooooooooo",
    "oooooooooooooooo",
    "oooooooooooooooo",
    "oooooooooooooooo",
    "oooooooooooooooo",
    "oooooooooooooooo",
    "oooooooooooooooo",
    "oooooooooooooooo",
    "oooooooooooooooo",
    "oooooooooooooooo",
    "offooooooooooooo",
    "offooooooooooooo",
    "oooofooooooooooo",
    "oooofooooooooook"
   ]
  },
  "tile_050": {
   "index": 50,
   "col": 2,
   "row": 6,
   "solid": false,
   "rows": [
    "oooooooooooooooo",
    "oooooooooooooooo",
    "oooooooooooooooo",
    "oooooooooooooooo",
    "oooooofooooooooo",
    "oooooofooooooooo",
    "ooffootoocoooooo",
    "ooffootoofoooooo",
    "ooooffotfnoooooo",
    "oooooooooooooooo",
    "oooooooooooooooo",
    "oooooooooooooooo",
    "oooooooooooooooo",
    "oooooooooooooooo",
    "oooooooooooooooo",
    "kooooooooooooooo"
   ]
  },
  "tile_051": {
   "index": 51,
   "col": 3,
   "row": 6,
   "solid": false,
   "rows": [
    "fftooooooooooooo",
    "gftooooooooooooo",
    "oooooootfooooooo",
    "oooooooooooooooo",
    "oooooooooooooooo",
    "oooooooooooooooo",
    "oooooooooooooooo",
    "oooooooooooooooo",
    "ooooooooooooooff",
    "ooooooooooofooff",
    "ooooooooooofooff",
    "ooooooooooooffoo",
    "ooooooooooootloo",
    "oooooooooooooooo",
    "oooooooooooooooo",
    "oooooooooooooooo"
   ]
  },
  "tile_052": {
   "index": 52,
   "col": 4,
   "row": 6,
   "solid": false,
   "rows": [
    "ooooooooooooonoo",
    "oooooooooooooooo",
    "oooooooooffooooo",
    "oooooooooooootoo",
    "oooooooooooontoo",
    "oooooooooooooooo",
    "oooooooooooooooo",
    "oooooooooooooooo",
    "oooooooooooooooo",
    "ooffoooooooooooo",
    "ooffoooooooooooo",
    "ffoooooooooooooo",
    "lloooooooooooooo",
    "oooooooooooooooo",
    "oooooooooooooooo",
    "oooooooooooooooo"
   ]
  },
  "tile_053": {
   "index": 53,
   "col": 5,
   "row": 6,
   "solid": false,
   "rows": [
    "oooooooooooooooo",
    "oooooooooooooooo",
    "oooooooooooooooo",
    "oooooooooooooooo",
    "oooooooooooooooo",
    "oooooooooooooooo",
    "oooooooooooooooo",
    "oooooooooooooooo",
    "oooooooooooooooo",
    "oooooooooooooooo",
    "oooooooooooooooo",
    "oooooooooooooooo",
    "ffoooooooooooooo",
    "ffoooooooooooooo",
    "oofooooooooooooo",
    "oofooooooooookko"
   ]
  },
  "tile_054": {
   "index": 54,
   "col": 6,
   "row": 6,
   "solid": false,
   "rows": [
    "ooooooooooooooof",
    "ooooooooooooooof",
    "oooooooooooooooo",
    "oooooooooooooooo",
    "oooffooooooooooo",
    "oooffooooooooooo",
    "ffoftootlooooooo",
    "ffoftnotlooooooo",
    "oofootftoooooooo",
    "oooooooooooooooo",
    "oooooooooooooooo",
    "oooooooooooooooo",
    "oooooooooooooooo",
    "oooooooooooooooo",
    "oooooooooooooooo",
    "oooooooooooooooo"
   ]
  },
  "tile_055": {
   "index": 55,
   "col": 7,
   "row": 6,
   "solid": false,
   "rows": [
    "fooooooooooooooo",
    "fooooooooooooooo",
    "oooooftooooooooo",
    "oooooooooooooooo",
    "oooooooooooooooo",
    "oooooooooooooooo",
    "oooooooooooooooo",
    "oooooooooooooooo",
    "ooooooooooooofoo",
    "oooooooooffootoo",
    "oooooooooffoofoo",
    "oooooooooooffoff",
    "ooooooooooottott",
    "oooooooooooooooo",
    "oooooooooooooooo",
    "oooooooooooooooo"
   ]
  },
  "tile_056": {
   "index": 56,
   "col": 0,
   "row": 7,
   "solid": false,
   "rows": [
    "oooooooooooooooo",
    "oooooooooooooooo",
    "oooooooooooooooo",
    "oooooooooooooooo",
    "oooooooooooooooo",
    "oooooooooooooooo",
    "oooooooooooooooo",
    "oooooooossnooooo",
    "oooooooossnooooo",
    "ooooossonnoossoo",
    "ooooossonnoossoo",
    "ooooosssooosdfoo",
    "oooooftsooostfoo",
    "ooooooocooofnooo",
    "oooooooooooooooo",
    "oooooooooooooooo"
   ]
  },
  "tile_057": {
   "index": 57,
   "col": 1,
   "row": 7,
   "solid": false,
   "rows": [
    "oooolooooooooook",
    "oooooooooooosoon",
    "ooooooooooootsso",
    "oooooooooooofsso",
    "ooooooooooooocfo",
    "oooooooooooooooo",
    "oooooooooooooooo",
    "oooooooooooooooo",
    "oooooooooooooooo",
    "oooooooooooooooo",
    "oooooooooooooooo",
    "oooooooooooooooo",
    "oooooooooooooooo",
    "oooooooooofftooo",
    "oooooooooooooooo",
    "oooooooooooooooo"
   ]
  },
  "tile_058": {
   "index": 58,
   "col": 2,
   "row": 7,
   "solid": false,
   "rows": [
    "kooooooooooooooo",
    "kossoooooooooooo",
    "osttoooooooooooo",
    "ostfoooooooooooo",
    "ofoooooooooooooo",
    "oooooooooooooloo",
    "ooooooooooooofoo",
    "ooooooooooooofoo",
    "oooooooooooooooo",
    "ooooooooooooooff",
    "oooooooooooooonn",
    "ooooooooootooooo",
    "ooooooooootooooo",
    "oooooooooofoofoo",
    "oooooooooolffooo",
    "oooooooooooffooo"
   ]
  },
  "tile_059": {
   "index": 59,
   "col": 3,
   "row": 7,
   "solid": false,
   "rows": [
    "oooooooooooooooo",
    "oooooofooooooooo",
    "ooofootooottoooo",
    "ooofoofoooffoooo",
    "ooolffootlffoooo",
    "ooooffolffoooooo",
    "oooooooooooooooo",
    "oooooooooooooooo",
    "oooooooooooooooo",
    "oooooooooooooooo",
    "oooooooooooooooo",
    "oooooooooooooooo",
    "oooooooooooooooo",
    "oooooooooooooooo",
    "oooooooooooooooo",
    "oooooooooooooooo"
   ]
  },
  "tile_060": {
   "index": 60,
   "col": 4,
   "row": 7,
   "solid": false,
   "rows": [
    "oooooooooooooooo",
    "oooooooooooooooo",
    "oooooooooooooooo",
    "oooooooooooooooo",
    "oooooooooooooooo",
    "oooooooooooooooo",
    "oooooooooooooooo",
    "ooooooossooooooo",
    "ooooooossooooooo",
    "ooolsoonnolssooo",
    "oooosoonnoossooo",
    "ooootskoossnkooo",
    "oooltskoosstfooo",
    "oooonffoocfooooo",
    "oooooooooooooooo",
    "oooooooooooooooo"
   ]
  },
  "tile_061": {
   "index": 61,
   "col": 5,
   "row": 7,
   "solid": false,
   "rows": [
    "oolooooooooookko",
    "oooooooooosookko",
    "oooooooooolssoos",
    "oooooooooofssoos",
    "oooooooooooccoof",
    "oooooooooooooooo",
    "oooooooooooooooo",
    "oooooooooooooooo",
    "oooooooooooooooo",
    "oooooooooooooooo",
    "oooooooooooooooo",
    "oooooooooooooooo",
    "oooooooooooooooo",
    "ooooooooofoooooo",
    "oooooooooooooooo",
    "oooooooooooooooo"
   ]
  },
  "tile_062": {
   "index": 62,
   "col": 6,
   "row": 7,
   "solid": false,
   "rows": [
    "oooooooooooooooo",
    "ssoooooooooooooo",
    "ttoooooooooooooo",
    "tfoooooooooooooo",
    "oooooooooooooooo",
    "oooooooooooloooo",
    "oooooooooootlooo",
    "oooooooooooflooo",
    "oooooooooooooooo",
    "oooooooooooofflo",
    "oooooooooooonnoo",
    "ooooooootooooooo",
    "ooooooootooooooo",
    "oooooooofoofoooo",
    "ooooooooocfooooo",
    "oooooooooffooooo"
   ]
  },
  "tile_063": {
   "index": 63,
   "col": 7,
   "row": 7,
   "solid": false,
   "rows": [
    "oooooooooooooooo",
    "oooofooooooooooo",
    "ofootoolfooooooo",
    "ocootooofooooooo",
    "ooffooffoooooooo",
    "ooffootfoooooooo",
    "oooooooooooooooo",
    "oooooooooooooooo",
    "oooooooooooooooo",
    "oooooooooooooooo",
    "oooooooooooooooo",
    "oooooooooooooooo",
    "oooooooooooooooo",
    "oooooooooooooooo",
    "oooooooooooooooo",
    "oooooooooooooooo"
   ]
  }
 }
}